penfolioop/__init__.py
penfolioop/constraints.py
penfolioop/optimizers.py
penfolioop/portfolio.py
penfolioop-0.2.1.dist-info/WHEEL
penfolioop-0.2.1.dist-info/METADATA
penfolioop-0.2.1.dist-info/RECORD
