Metadata-Version: 2.3
Name: penfolioop
Version: 0.2.1
Summary: Portfolio Optimization for Pension Funds
Requires-Dist: numpy
Requires-Dist: pandas
Requires-Dist: cvxpy
Requires-Dist: pydantic
Requires-Dist: ruff==0.9.10 ; extra == 'dev'
Requires-Dist: pre-commit==4.1.0 ; extra == 'dev'
Requires-Dist: pdoc3 ; extra == 'docs'
Requires-Dist: matplotlib ; extra == 'docs'
Requires-Dist: plotly ; extra == 'docs'
Requires-Dist: seaborn ; extra == 'docs'
Requires-Dist: nbformat==5.4.0 ; extra == 'docs'
Requires-Dist: ipython ; extra == 'docs'
Requires-Dist: notebook ; extra == 'docs'
Requires-Dist: ipywidgets ; extra == 'docs'
Requires-Dist: pytest ; extra == 'tests'
Requires-Dist: pytest-cov ; extra == 'tests'
Requires-Python: >=3.11
Provides-Extra: dev
Provides-Extra: docs
Provides-Extra: tests
